dlpack/__init__.py
dlpack/_version.py
dlpack/buffer.py
dlpack/capsule.py
dlpack/tests/__init__.py
dlpack/tests/test_buffer.py
dlpack/tests/test_capsule.py
dlpack/tests/test_dlpack.py
pydlpack-0.2.1.dist-info/LICENSE
pydlpack-0.2.1.dist-info/METADATA
pydlpack-0.2.1.dist-info/WHEEL
pydlpack-0.2.1.dist-info/top_level.txt
pydlpack-0.2.1.dist-info/RECORD
