Metadata-Version: 2.1
Name: pydlpack
Version: 0.2.1
Summary: DLPack data exchange interface in Python
Author-email: Pearu Peterson <pearu.peterson@gmail.com>
License: BSD 3-Clause License
Project-URL: Home, https://github.com/pearu/pydlpack
Project-URL: Source, https://github.com/pearu/pydlpack
Classifier: Intended Audience :: Developers
Classifier: License :: OSI Approved :: BSD License
Classifier: Operating System :: OS Independent
Classifier: Programming Language :: Python :: 3
Classifier: Topic :: Scientific/Engineering
Classifier: Topic :: Software Development
Requires-Python: >=3.9
License-File: LICENSE
Provides-Extra: dev
Requires-Dist: pre-commit ; extra == 'dev'
Provides-Extra: test
Requires-Dist: pytest ; extra == 'test'
Requires-Dist: coverage ; extra == 'test'
Requires-Dist: pytest-mock ; extra == 'test'
Requires-Dist: numpy ; extra == 'test'
